pythaidate/__init__.py
pythaidate/cli.py
pythaidate/constants.py
pythaidate/csdate.py
pythaidate/helpers.py
pythaidate/julianday.py
pythaidate/lsyear.py
pythaidate/pakdate.py
pythaidate-0.2.0.dist-info/LICENSE.txt
pythaidate-0.2.0.dist-info/METADATA
pythaidate-0.2.0.dist-info/WHEEL
pythaidate-0.2.0.dist-info/entry_points.txt
pythaidate-0.2.0.dist-info/top_level.txt
pythaidate-0.2.0.dist-info/RECORD
