Metadata-Version: 2.1
Name: pythaidate
Version: 0.2.0
Summary: Date classes for Thai calendar systems.
Home-page: https://github.com/hmmbug/pythaidate
Author: Mark Hollow
Author-email: dev@hmmbug.com
Project-URL: Bug Reports, https://github.com/hmmbug/pythaidate/issues
Project-URL: Source, https://github.com/hmmbug/pythaidate/
Keywords: date,calendar,thai,development,library
Classifier: Development Status :: 3 - Alpha
Classifier: Intended Audience :: Developers
Classifier: Topic :: Software Development :: Libraries
Classifier: Topic :: Software Development :: Localization
Classifier: License :: OSI Approved :: MIT License
Classifier: Programming Language :: Python :: 3
Classifier: Programming Language :: Python :: 3.8
Classifier: Programming Language :: Python :: 3.9
Classifier: Programming Language :: Python :: 3.10
Classifier: Programming Language :: Python :: 3.11
Classifier: Programming Language :: Python :: 3.12
Classifier: Programming Language :: Python :: 3 :: Only
Requires-Python: >=3.8, <4
License-File: LICENSE.txt
Provides-Extra: dev
Requires-Dist: check-manifest ; extra == 'dev'
Provides-Extra: test
Requires-Dist: coverage ; extra == 'test'
